pyaatlibs/__init__.py
pyaatlibs/aatapp.py
pyaatlibs/activitystatemachine.py
pyaatlibs/adbutils.py
pyaatlibs/appinterface.py
pyaatlibs/argutils.py
pyaatlibs/audiofunction.py
pyaatlibs/audiosignalframelogger.py
pyaatlibs/audiothread.py
pyaatlibs/audioworker.py
pyaatlibs/logcatlistener.py
pyaatlibs/logger.py
pyaatlibs/signalanalyzer.py
pyaatlibs/signalmatcher.py
pyaatlibs/timeutils.py
pyaatlibs/trials.py
pyaatlibs/apk/audiofunctionsdemo.apk
pyaatlibs/apk/audioworker.apk
pyaatlibs/tests/audioworker_test.py
pyaatlibs/tests/conftest.py
python_audio_autotest-1.5.10.dist-info/LICENSE
python_audio_autotest-1.5.10.dist-info/METADATA
python_audio_autotest-1.5.10.dist-info/WHEEL
python_audio_autotest-1.5.10.dist-info/top_level.txt
python_audio_autotest-1.5.10.dist-info/RECORD
