Metadata-Version: 2.2
Name: python-audio-autotest
Version: 1.5.10
Summary: This is a auto-testing framework of audio functions for Android devices.
Home-page: https://github.com/HW-Lee/AudioAutoTest
Author: Hao-Wei Lee
Author-email: hwinnerlee@gmail.com, hwlee@google.com
Classifier: Programming Language :: Python :: 3
Classifier: License :: OSI Approved :: Apache Software License
Classifier: Operating System :: OS Independent
License-File: LICENSE
Requires-Dist: androidviewclient==22.3.1
Requires-Dist: numpy==1.20.3
Requires-Dist: scipy==1.7.3
Requires-Dist: scikit-learn==1.0.2
Requires-Dist: matplotlib==3.5.3
Requires-Dist: librosa==0.9.2
Requires-Dist: sounddevice==0.4.5
Dynamic: author
Dynamic: author-email
Dynamic: classifier
Dynamic: description
Dynamic: description-content-type
Dynamic: home-page
Dynamic: requires-dist
Dynamic: summary
